xlwings_server/.env.template
xlwings_server/__init__.py
xlwings_server/_version.py
xlwings_server/cli.py
xlwings_server/config.py
xlwings_server/databases.py
xlwings_server/dependencies.py
xlwings_server/hotreload.py
xlwings_server/main.py
xlwings_server/object_handles.py
xlwings_server/security_headers.json
xlwings_server/templates.py
xlwings_server/utils.py
xlwings_server/auth/__init__.py
xlwings_server/auth/custom/__init__.py
xlwings_server/auth/entraid/__init__.py
xlwings_server/auth/entraid/jwks.py
xlwings_server/azure_functions_templates/.funcignore
xlwings_server/azure_functions_templates/function_app.py
xlwings_server/azure_functions_templates/host.json
xlwings_server/azure_functions_templates/local.settings.json
xlwings_server/build_utils/__init__.py
xlwings_server/build_utils/static_file_hasher.py
xlwings_server/custom_functions/__init__.py
xlwings_server/custom_functions/examples.py
xlwings_server/custom_scripts/__init__.py
xlwings_server/custom_scripts/examples.py
xlwings_server/docker_templates/.dockerignore
xlwings_server/docker_templates/Dockerfile
xlwings_server/docker_templates/docker-compose.yaml
xlwings_server/models/__init__.py
xlwings_server/models/user.py
xlwings_server/routers/__init__.py
xlwings_server/routers/manifest.py
xlwings_server/routers/root.py
xlwings_server/routers/socketio.py
xlwings_server/routers/taskpane.py
xlwings_server/routers/xlwings.py
xlwings_server/serializers/__init__.py
xlwings_server/serializers/default_serializer.py
xlwings_server/serializers/dictionary_serializer.py
xlwings_server/serializers/framework.py
xlwings_server/serializers/numpy_serializer.py
xlwings_server/serializers/pandas_serializer.py
xlwings_server/static/css/core.css
xlwings_server/static/css/style.css
xlwings_server/static/images/favicon.png
xlwings_server/static/images/xlwings-16.png
xlwings_server/static/images/xlwings-32.png
xlwings_server/static/images/xlwings-64.png
xlwings_server/static/images/xlwings-80.png
xlwings_server/static/js/auth.js
xlwings_server-1.1.1.dist-info/METADATA
xlwings_server-1.1.1.dist-info/WHEEL
xlwings_server-1.1.1.dist-info/entry_points.txt
xlwings_server-1.1.1.dist-info/licenses/LICENSE.md
xlwings_server-1.1.1.dist-info/RECORD
